{
  "schemaVersion": 1,
  "feature": "innercircle-chama-fixes",
  "displayName": "InnerCircle Chama - Review Fixes",
  "memoryEpicId": "cn-svpj9w",
  "decisions": [
    { "area": "B1-ledger-balance", "decision": "Add isNormalDebit() to AccountType enum; branch balance update by account type", "rationale": "ASSET/EXPENSE increase on debit, LIABILITY/EQUITY/REVENUE increase on credit. Standard double-entry accounting." },
    { "area": "B2-partial-payment", "decision": "Add amountPaid field to RepaymentSchedule + Liquibase migration", "rationale": "Track partial payment state. Schedule paid only when amountPaid >= totalAmount." },
    { "area": "B3-final-installment", "decision": "Recalculate interest on actual remaining principal for last installment", "rationale": "Interest must reflect true balance, not stale value from prior iteration." },
    { "area": "B4-hardcoded-secrets", "decision": "Externalize to application.yml with env var placeholders", "rationale": "Standard Spring externalized config. No secrets in source." },
    { "area": "B5-permit-all", "decision": "Change .anyRequest().permitAll() to .authenticated()", "rationale": "Secure default: all unmapped routes require authentication." },
    { "area": "B6-idor", "decision": "Extract member ID from JWT; MEMBER can only access own data; TREASURER/ADMIN access any", "rationale": "Uses @PreAuthorize with SecurityContextHolder for authorization checks." },
    { "area": "B7-csv-injection", "decision": "Prefix formula characters with single quote in escapeCsv()", "rationale": "OWASP recommendation for CSV injection prevention." },
    { "area": "B8-fk-constraints", "decision": "Single new Liquibase changeset with ON DELETE RESTRICT FKs", "rationale": "Financial data should never cascade-delete. One changeset for all FKs." },
    { "area": "W1-rsa-keys", "decision": "Load from application.yml properties with dev fallback", "rationale": "Persistent keys survive restarts and support clustering." },
    { "area": "W5-uuid-v7", "decision": "Replace custom impl with java-uuid-generator library", "rationale": "Battle-tested library eliminates bit manipulation risk." },
    { "area": "W6-exception-logging", "decision": "Add log.error to generic exception handler", "rationale": "Stack traces must be logged for debugging." },
    { "area": "W7-optimistic-locking", "decision": "Add @Version to BaseEntity + migration", "rationale": "Financial system needs concurrency protection." },
    { "area": "W8-disbursement-race", "decision": "Single save with REPAYING status", "rationale": "Eliminates intermediate DISBURSED state." },
    { "area": "W9-entry-number", "decision": "Use DB sequence for journal entry numbers", "rationale": "Natively atomic, no race conditions." },
    { "area": "W10-interest-rate", "decision": "Add @DecimalMax(100.0) validation", "rationale": "Reasonable upper bound for chama loans." },
    { "area": "W11-reference-number", "decision": "Use UUID v7 substring for uniqueness", "rationale": "Time-ordered, unique, non-predictable." },
    { "area": "W15-date-validation", "decision": "Add fromDate < toDate validation", "rationale": "Prevents nonsensical date ranges." },
    { "area": "W17-pdf-pagebreak", "decision": "Fix page break to continue on new page", "rationale": "Current break truncates output silently." },
    { "area": "W18-rollbacks", "decision": "Add rollback definitions to existing changesets", "rationale": "Enables safe rollback of any migration." },
    { "area": "W19-unique-constraints", "decision": "Add UNIQUE on reference_number columns", "rationale": "Prevents duplicate reference numbers at DB level." },
    { "area": "W2-actuator-swagger", "decision": "Restrict actuator to ADMIN; Swagger behind auth in prod", "rationale": "Defense in depth for information disclosure." }
  ],
  "constraints": [
    "All fixes must compile with mvn compile -q",
    "Liquibase migrations must be additive (new changesets only)",
    "Existing API contracts must not break",
    "Module isolation: no new cross-module dependencies",
    "Financial calculation fixes are highest priority"
  ],
  "planGroups": [
    { "plan": "01", "scope": "Financial calculation fixes", "issues": ["B1", "B3", "W8", "W9"], "modules": ["sacco-ledger", "sacco-loan"] },
    { "plan": "02", "scope": "Loan repayment tracking", "issues": ["B2"], "modules": ["sacco-loan", "sacco-app"] },
    { "plan": "03", "scope": "Security hardening", "issues": ["B4", "B5", "W1", "W2", "W10"], "modules": ["sacco-security", "sacco-loan"] },
    { "plan": "04", "scope": "Authorization & IDOR", "issues": ["B6", "W15"], "modules": ["sacco-reporting"] },
    { "plan": "05", "scope": "CSV injection & PDF fix", "issues": ["B7", "W17"], "modules": ["sacco-reporting"] },
    { "plan": "06", "scope": "Data integrity & common fixes", "issues": ["B8", "W5", "W6", "W7", "W11", "W18", "W19"], "modules": ["sacco-common", "sacco-payout", "sacco-app"] }
  ],
  "relatedCode": [
    "sacco-ledger/src/main/java/com/innercircle/sacco/ledger/service/LedgerServiceImpl.java",
    "sacco-ledger/src/main/java/com/innercircle/sacco/ledger/entity/AccountType.java",
    "sacco-loan/src/main/java/com/innercircle/sacco/loan/service/LoanServiceImpl.java",
    "sacco-loan/src/main/java/com/innercircle/sacco/loan/service/RepaymentScheduleGenerator.java",
    "sacco-loan/src/main/java/com/innercircle/sacco/loan/entity/RepaymentSchedule.java",
    "sacco-loan/src/main/java/com/innercircle/sacco/loan/dto/LoanApplicationRequest.java",
    "sacco-security/src/main/java/com/innercircle/sacco/security/config/AuthorizationServerConfig.java",
    "sacco-security/src/main/java/com/innercircle/sacco/security/config/SecurityConfig.java",
    "sacco-reporting/src/main/java/com/innercircle/sacco/reporting/controller/DashboardController.java",
    "sacco-reporting/src/main/java/com/innercircle/sacco/reporting/controller/ReportController.java",
    "sacco-reporting/src/main/java/com/innercircle/sacco/reporting/controller/ExportController.java",
    "sacco-reporting/src/main/java/com/innercircle/sacco/reporting/service/ExportServiceImpl.java",
    "sacco-common/src/main/java/com/innercircle/sacco/common/model/BaseEntity.java",
    "sacco-common/src/main/java/com/innercircle/sacco/common/util/UuidGenerator.java",
    "sacco-common/src/main/java/com/innercircle/sacco/common/exception/GlobalExceptionHandler.java",
    "sacco-payout/src/main/java/com/innercircle/sacco/payout/service/PayoutServiceImpl.java"
  ],
  "research": [],
  "timestamp": "2026-02-15T00:00:00Z"
}
